<?xml version="1.0" encoding="UTF-8"?>

<!DOCTYPE mapper PUBLIC "-//mybatis.org//DTD Mapper 3.0//EN" "http://mybatis.org/dtd/mybatis-3-mapper.dtd">

<mapper namespace="com.sist.haebollangce.common.mapper.InterMapper">

   <select id="challengeList" resultType="com.sist.haebollangce.challenge.dao.challengeVO">
     SELECT
     b.fk_userid AS fkuserid,
     a.category_name AS category_name,
     b.challenge_name AS challengeName,
     b.thumbnail as thumbnail,
     b.content,
     b.startDate,
     b.fk_during_type,
     c.set_date,
     b.member_count,
     b.fk_category_code,
     a.category_code AS category_code,
     b.challenge_code AS challengeCode,
     f.frequency AS frequency
     FROM
     tbl_challenge b
     JOIN tbl_category a ON b.fk_category_code = a.category_code
     JOIN tbl_challenge_during c ON b.fk_during_type = c.during_type
     JOIN tbl_certify_freq f ON b.fk_freq_type = f.freq_type
     
     
     
   </select>

   <select id="categoryList" resultType="com.sist.haebollangce.challenge.dao.challengeVO">
      select category_code, category_name
      from TBL_CATEGORY
   </select>
   

   <select id="challengelist" resultType="com.sist.haebollangce.challenge.dao.challengeVO">
     SELECT
    b.fk_userid AS fkuserid,
    a.category_name AS category_name,
    b.challenge_name AS challengeName,
    b.thumbnail AS thumbnail,
    b.content,
    b.startDate,
    b.fk_during_type,
    c.set_date,
    b.member_count,
    b.fk_category_code,
    a.category_code AS category_code,
    b.challenge_code AS challenge_code,
    f.frequency AS frequency
   FROM
    tbl_challenge b
    JOIN tbl_category a ON b.fk_category_code = a.category_code
    JOIN tbl_challenge_during c ON b.fk_during_type = c.during_type
    JOIN tbl_certify_freq f ON b.fk_freq_type = f.freq_type
   <where>
     <if test="category_code != null and category_name != '전체'">
       AND a.category_code = #{categoryCode}
     </if>
   </where>
   </select>


   <select id="challViewWithNoAddCount" parameterType="HashMap" resultType="com.sist.haebollangce.challenge.dao.challengeVO">
     SELECT
     m.pw AS pw,
     a.category_name AS category_name,
     b.challenge_name AS challengeName,
     b.thumbnail AS thumbnail,
     b.content,
     b.startDate,
     b.fk_during_type,
     c.set_date,
     b.member_count,
     b.fk_category_code,
     a.category_code AS category_code,
     b.challenge_code AS challengeCode,
     b.fk_userid AS fkUserid
      FROM
           tbl_user m
      JOIN
           tbl_challenge b ON m.userid = b.fk_userid
      JOIN
           tbl_category a ON b.fk_category_code = a.category_code
      JOIN
           tbl_challenge_during c ON b.fk_during_type = c.during_type
      WHERE
       b.challenge_code = #{challengeCode}
   </select>

 
   <delete id="challengedel" parameterType="HashMap">
       DELETE FROM TBL_CHALLENGE
       WHERE challenge_code = #{challengeCode}
   </delete>
   
   <select id="index_loungeList" resultType="com.sist.haebollangce.lounge.model.LoungeBoardDTO">
      select fk_userid, content, subject, name, readcount, likeCount, commentCount, readCount, thumbnail, seq
      from TBL_LOUNGE_BOARD
   </select>
   
   
   
</mapper>